vasbotlauncher/__init__.py
vasbotlauncher/launcher.py
vasbotlauncher-0.2.0.dist-info/METADATA
vasbotlauncher-0.2.0.dist-info/WHEEL
vasbotlauncher-0.2.0.dist-info/entry_points.txt
vasbotlauncher-0.2.0.dist-info/top_level.txt
vasbotlauncher-0.2.0.dist-info/RECORD
