Metadata-Version: 2.4
Name: vasbotlauncher
Version: 0.2.0
Summary: Launcher A Discord bot written in Python.
Author: DEAMJAVA
Author-email: deamminecraft3@gmail.com
Requires-Python: >=3.12
Requires-Dist: requests
Dynamic: author
Dynamic: author-email
Dynamic: description
Dynamic: description-content-type
Dynamic: requires-dist
Dynamic: requires-python
Dynamic: summary
